mensajes/__init__.py
mensajes/bienvenida/__init__.py
mensajes/bienvenida/saludos.py
mensajes/despedida/__init__.py
mensajes/despedida/despedirse.py
tests/__init__.py
tests/test_hola.py
Mensajes_laxus-6.0.dist-info/LICENSE
Mensajes_laxus-6.0.dist-info/METADATA
Mensajes_laxus-6.0.dist-info/WHEEL
Mensajes_laxus-6.0.dist-info/top_level.txt
Mensajes_laxus-6.0.dist-info/RECORD
