Metadata-Version: 2.1
Name: Mensajes-laxus
Version: 6.0
Summary: paquete para saludos y despedidas
Home-page: 
Author: Elias Arias Muñoz
Author-email: eaarias320@gmail.com
Classifier: Environment :: Console
Classifier: Intended Audience :: Developers
Classifier: License :: OSI Approved :: MIT License
Classifier: Operating System :: OS Independent
Classifier: Programming Language :: Python :: 3.12
Classifier: Topic :: Utilities
License-File: LICENSE
Requires-Dist: numpy >=1.26.4
